sfdclib/__init__.py
sfdclib/bulk.py
sfdclib/logger.py
sfdclib/messages.py
sfdclib/metadata.py
sfdclib/rest.py
sfdclib/session.py
sfdclib/tooling.py
sfdclib-0.2.24.dist-info/METADATA
sfdclib-0.2.24.dist-info/RECORD
sfdclib-0.2.24.dist-info/WHEEL
sfdclib-0.2.24.dist-info/top_level.txt
