Metadata-Version: 2.1
Name: sfdclib
Version: 0.2.24
Summary: SFDClib is a Salesforce.com Metadata API and Tooling API client built for Python 2.7, 3.3 and 3.4.
Home-page: https://github.com/rbauction/sfdclib
Author: Andrey Shevtsov
Author-email: ashevtsov@rbauction.com
License: MIT
Keywords: python salesforce salesforce.com metadata tooling api
Platform: UNKNOWN
Classifier: Development Status :: 4 - Beta
Classifier: License :: OSI Approved :: MIT License
Classifier: Intended Audience :: Developers
Classifier: Intended Audience :: System Administrators
Classifier: Operating System :: OS Independent
Classifier: Topic :: Internet :: WWW/HTTP
Classifier: Programming Language :: Python :: 2.7
Classifier: Programming Language :: Python :: 3.3
Classifier: Programming Language :: Python :: 3.4
Requires-Dist: requests[security]
